code_time_tracker/__init__.py
code_time_tracker/analytics.py
code_time_tracker/cli.py
code_time_tracker/data_storage.py
code_time_tracker/file_monitor.py
code_time_tracker/time_tracker.py
code_time_tracker/visualization.py
kyu_nahi_horahi_padhai-0.1.0.dist-info/LICENSE
kyu_nahi_horahi_padhai-0.1.0.dist-info/METADATA
kyu_nahi_horahi_padhai-0.1.0.dist-info/WHEEL
kyu_nahi_horahi_padhai-0.1.0.dist-info/entry_points.txt
kyu_nahi_horahi_padhai-0.1.0.dist-info/top_level.txt
kyu_nahi_horahi_padhai-0.1.0.dist-info/RECORD
